multi_notifier/__init__.py
multi_notifier/__version__.py
multi_notifier/exceptions.py
multi_notifier/send_handler.py
multi_notifier/connectors/__init__.py
multi_notifier/connectors/connector_mail.py
multi_notifier/connectors/connector_mail_imap.py
multi_notifier/connectors/connector_telegram.py
multi_notifier/connectors/exceptions.py
multi_notifier/connectors/interface.py
multi_notifier-0.5.0.dist-info/LICENSE
multi_notifier-0.5.0.dist-info/METADATA
multi_notifier-0.5.0.dist-info/WHEEL
multi_notifier-0.5.0.dist-info/top_level.txt
multi_notifier-0.5.0.dist-info/RECORD
